airsim/__init__.py
airsim/client.py
airsim/pfm.py
airsim/types.py
airsim/utils.py
carla/__init__.py
carla/command.pyi
carla/libcarla.cp39-win_amd64.pyd
carla/libcarla.pyi
hutb-2.2.1.dist-info/METADATA
hutb-2.2.1.dist-info/WHEEL
hutb-2.2.1.dist-info/top_level.txt
hutb-2.2.1.dist-info/RECORD
