Metadata-Version: 2.2
Name: hutb
Version: 2.2.1
Summary: Python API for communicating with the HUTB simulator.
Home-page: https://github.com/OpenHUTB/hutb
Author: OpenHUTB
Author-email: whd@hutb.edu.cn
License: MIT License
Requires-Dist: msgpack-rpc-python
Requires-Dist: numpy
Requires-Dist: opencv-contrib-python
Dynamic: author
Dynamic: author-email
Dynamic: description
Dynamic: description-content-type
Dynamic: home-page
Dynamic: license
Dynamic: requires-dist
Dynamic: summary
